govtech_csg_xcg/dangerousrequests/__init__.py
govtech_csg_xcg/dangerousrequests/apps.py
govtech_csg_xcg/dangerousrequests/advocate/__init__.py
govtech_csg_xcg/dangerousrequests/advocate/adapters.py
govtech_csg_xcg/dangerousrequests/advocate/addrvalidator.py
govtech_csg_xcg/dangerousrequests/advocate/api.py
govtech_csg_xcg/dangerousrequests/advocate/connection.py
govtech_csg_xcg/dangerousrequests/advocate/connectionpool.py
govtech_csg_xcg/dangerousrequests/advocate/exceptions.py
govtech_csg_xcg/dangerousrequests/advocate/futures.py
govtech_csg_xcg/dangerousrequests/advocate/poolmanager.py
govtech_csg_xcg/dangerousrequests/patch/__init__.py
govtech_csg_xcg/dangerousrequests/patch/patch.py
govtech_csg_xcg/dangerousrequests/patch/utils.py
govtech_csg_xcg_dangerousrequests-0.1.0.dist-info/LICENSE
govtech_csg_xcg_dangerousrequests-0.1.0.dist-info/METADATA
govtech_csg_xcg_dangerousrequests-0.1.0.dist-info/WHEEL
govtech_csg_xcg_dangerousrequests-0.1.0.dist-info/top_level.txt
govtech_csg_xcg_dangerousrequests-0.1.0.dist-info/RECORD
